sharing_configs/__init__.py
sharing_configs/admin.py
sharing_configs/apps.py
sharing_configs/client_util.py
sharing_configs/exceptions.py
sharing_configs/forms.py
sharing_configs/models.py
sharing_configs/utils.py
sharing_configs/migrations/0001_initial.py
sharing_configs/migrations/0002_alter_sharingconfigsconfig_id.py
sharing_configs/migrations/0003_alter_sharingconfigsconfig_id.py
sharing_configs/migrations/0004_alter_sharingconfigsconfig_id.py
sharing_configs/migrations/0005_alter_sharingconfigsconfig_options_and_more.py
sharing_configs/migrations/__init__.py
sharing_configs/static/sharing_configs/ajax_in_action.js
sharing_configs/static/sharing_configs/jquery_in_action.js
sharing_configs/templates/sharing_configs/admin/change_form.html
sharing_configs/templates/sharing_configs/admin/change_list.html
sharing_configs/templates/sharing_configs/admin/export.html
sharing_configs/templates/sharing_configs/admin/import.html
sharing_configs-0.1.2.dist-info/AUTHORS
sharing_configs-0.1.2.dist-info/LICENSE.md
sharing_configs-0.1.2.dist-info/METADATA
sharing_configs-0.1.2.dist-info/WHEEL
sharing_configs-0.1.2.dist-info/top_level.txt
sharing_configs-0.1.2.dist-info/RECORD
