Metadata-Version: 2.1
Name: sharing-configs
Version: 0.1.2
Summary: Django admin package to interact with Sharing Configs API
Home-page: https://github.com/maykinmedia/sharing-configs
Author: Maykin Media
Author-email: support@maykinmedia.nl
License: EUPL
Keywords: django,github
Platform: UNKNOWN
Classifier: Development Status :: 3 - Alpha
Classifier: Framework :: Django
Classifier: Framework :: Django :: 2.2
Classifier: Framework :: Django :: 3.2
Classifier: Intended Audience :: Developers
Classifier: Operating System :: Unix
Classifier: Operating System :: MacOS
Classifier: Operating System :: Microsoft :: Windows
Classifier: Programming Language :: Python :: 3.7
Classifier: Programming Language :: Python :: 3.8
Classifier: Programming Language :: Python :: 3.9
Classifier: Topic :: Software Development :: Libraries :: Python Modules
License-File: LICENSE.md
License-File: AUTHORS
Requires-Dist: django (>=2.2)
Requires-Dist: django-solo
Requires-Dist: requests
Provides-Extra: coverage
Requires-Dist: pytest-cov ; extra == 'coverage'
Provides-Extra: docs
Requires-Dist: sphinx ; extra == 'docs'
Requires-Dist: sphinx-rtd-theme ; extra == 'docs'
Provides-Extra: pep8
Requires-Dist: flake8 ; extra == 'pep8'
Provides-Extra: release
Requires-Dist: bumpversion ; extra == 'release'
Requires-Dist: twine ; extra == 'release'
Provides-Extra: tests
Requires-Dist: pytest ; extra == 'tests'
Requires-Dist: pytest-django ; extra == 'tests'
Requires-Dist: requests-mock ; extra == 'tests'
Requires-Dist: Faker ; extra == 'tests'
Requires-Dist: factory-boy ; extra == 'tests'
Requires-Dist: tox ; extra == 'tests'
Requires-Dist: black ; extra == 'tests'
Requires-Dist: isort ; extra == 'tests'
